sat_mouse_mover/__init__.py
sat_mouse_mover/__main__.py
sat_mouse_mover/watch.py
sat_mouse_mover-0.0.5.dist-info/METADATA
sat_mouse_mover-0.0.5.dist-info/WHEEL
sat_mouse_mover-0.0.5.dist-info/entry_points.txt
sat_mouse_mover-0.0.5.dist-info/top_level.txt
sat_mouse_mover-0.0.5.dist-info/RECORD
